setup.py
dogic/__init__.py
dogic/__main__.py
dogic.egg-info/PKG-INFO
dogic.egg-info/SOURCES.txt
dogic.egg-info/dependency_links.txt
dogic.egg-info/requires.txt
dogic.egg-info/top_level.txt